{"cameraMode":{"drawMode":0,"name":"Shaded","section":"Shading Mode"},"sceneLighting":true,"audioPlay":false,"sceneViewState":{"m_AlwaysRefresh":false,"showFog":true,"showSkybox":true,"showFlares":true,"showImageEffects":true,"showParticleSystems":true,"showVisualEffectGraphs":true,"m_FxEnabled":true},"in2DMode":false,"pivot":{"x":-285.73382568359377,"y":3.1557273864746095,"z":303.92626953125},"rotation":{"x":0.05094810202717781,"y":0.915388822555542,"z":-0.12266334891319275,"w":0.38013166189193728},"size":23.36504364013672,"orthographic":false}